fletcarousel/__init__.py
fletcarousel/attributes.py
fletcarousel/fletcarousel.py
fletcarousel/horizontal.py
fletcarousel-0.0.14.dist-info/LICENSE
fletcarousel-0.0.14.dist-info/METADATA
fletcarousel-0.0.14.dist-info/WHEEL
fletcarousel-0.0.14.dist-info/top_level.txt
fletcarousel-0.0.14.dist-info/RECORD
