Metadata-Version: 2.1
Name: fletcarousel
Version: 0.0.14
Summary: Simple carousel sliders for flet framework
Home-page: https://github.com/naderidev/flet-carousel
Author: naderidev
Author-email: mohammadrezanaderi84@gmail.com
License: LICENSE
Keywords: flet,carousel,slideshow,slider,python,flet-carousel,fletcarousel
Classifier: Development Status :: 4 - Beta
Classifier: Intended Audience :: Developers
Classifier: Topic :: Software Development :: Libraries :: Python Modules
Classifier: Programming Language :: Python :: 3.10
Classifier: License :: OSI Approved :: MIT License
Requires-Python: >=3.9
License-File: LICENSE
